COPYRIGHT.txt
LICENSE.txt
MANIFEST.in
README.txt
setup.cfg
setup.py
tox.ini
version.py
docs/HISTORY.txt
docs/Makefile
docs/api.txt
docs/conf.py
docs/index.txt
gs/__init__.py
gs.form.egg-info/PKG-INFO
gs.form.egg-info/SOURCES.txt
gs.form.egg-info/dependency_links.txt
gs.form.egg-info/entry_points.txt
gs.form.egg-info/namespace_packages.txt
gs.form.egg-info/not-zip-safe
gs.form.egg-info/requires.txt
gs.form.egg-info/top_level.txt
gs/form/__init__.py
gs/form/httplib.py
gs/form/postmultipart.py
gs/form/test/__init__.py
gs/form/test/contenttype.py
gs/form/test/encode.py
gs/form/test/post.py
gs/form/test/test_all.py